smartwordcloudgenerator/DroidSansMono.ttf
smartwordcloudgenerator/__init__.py
smartwordcloudgenerator/main.py
smartwordcloudgenerator/data/corpora/omw-1.4.zip
smartwordcloudgenerator/data/corpora/stopwords.zip
smartwordcloudgenerator/data/corpora/wordnet.zip
smartwordcloudgenerator/data/corpora/stopwords/README
smartwordcloudgenerator/data/corpora/stopwords/arabic
smartwordcloudgenerator/data/corpora/stopwords/azerbaijani
smartwordcloudgenerator/data/corpora/stopwords/basque
smartwordcloudgenerator/data/corpora/stopwords/bengali
smartwordcloudgenerator/data/corpora/stopwords/catalan
smartwordcloudgenerator/data/corpora/stopwords/chinese
smartwordcloudgenerator/data/corpora/stopwords/danish
smartwordcloudgenerator/data/corpora/stopwords/dutch
smartwordcloudgenerator/data/corpora/stopwords/english
smartwordcloudgenerator/data/corpora/stopwords/finnish
smartwordcloudgenerator/data/corpora/stopwords/french
smartwordcloudgenerator/data/corpora/stopwords/german
smartwordcloudgenerator/data/corpora/stopwords/greek
smartwordcloudgenerator/data/corpora/stopwords/hebrew
smartwordcloudgenerator/data/corpora/stopwords/hinglish
smartwordcloudgenerator/data/corpora/stopwords/hungarian
smartwordcloudgenerator/data/corpora/stopwords/indonesian
smartwordcloudgenerator/data/corpora/stopwords/italian
smartwordcloudgenerator/data/corpora/stopwords/kazakh
smartwordcloudgenerator/data/corpora/stopwords/nepali
smartwordcloudgenerator/data/corpora/stopwords/norwegian
smartwordcloudgenerator/data/corpora/stopwords/portuguese
smartwordcloudgenerator/data/corpora/stopwords/romanian
smartwordcloudgenerator/data/corpora/stopwords/russian
smartwordcloudgenerator/data/corpora/stopwords/slovene
smartwordcloudgenerator/data/corpora/stopwords/spanish
smartwordcloudgenerator/data/corpora/stopwords/swedish
smartwordcloudgenerator/data/corpora/stopwords/tajik
smartwordcloudgenerator/data/corpora/stopwords/turkish
smartwordcloudgenerator/data/tokenizers/punkt_tab.zip
smartwordcloudgenerator-1.4.dist-info/LICENSE
smartwordcloudgenerator-1.4.dist-info/METADATA
smartwordcloudgenerator-1.4.dist-info/WHEEL
smartwordcloudgenerator-1.4.dist-info/top_level.txt
smartwordcloudgenerator-1.4.dist-info/RECORD
